ppmail/__init__.py
ppmail/__main__.py
ppmail/__version__.py
ppmail/mailer.py
ppmail/ppmail.py
ppmail-2.2.2.dist-info/LICENSE.txt
ppmail-2.2.2.dist-info/METADATA
ppmail-2.2.2.dist-info/WHEEL
ppmail-2.2.2.dist-info/entry_points.txt
ppmail-2.2.2.dist-info/top_level.txt
ppmail-2.2.2.dist-info/RECORD
