Metadata-Version: 2.1
Name: ppmail
Version: 2.2.2
Summary: Tool to send messages via Sendgrid/Slack
Home-page: https://github.com/peterpakos/ppmail
Author: Peter Pakos
Author-email: peter.pakos@wandisco.com
License: GPLv3
Keywords: mail mailer sendgrid slack
Platform: UNKNOWN
Classifier: Programming Language :: Python :: 2
Classifier: Programming Language :: Python :: 2.7
Classifier: Programming Language :: Python :: 3
Classifier: Programming Language :: Python :: 3.3
Classifier: Programming Language :: Python :: 3.4
Classifier: Programming Language :: Python :: 3.5
Classifier: Programming Language :: Python :: 3.6
Classifier: Programming Language :: Python :: 3.7
Classifier: License :: OSI Approved :: GNU General Public License v3 (GPLv3)
Classifier: Topic :: Communications :: Email
Classifier: Topic :: Communications :: Chat
Requires-Dist: pplogger
Requires-Dist: ppconfig
Requires-Dist: sendgrid
Requires-Dist: slackclient (==1.3.1)
